happy/Hap.py
happy/__init__.py
happy/autoestimate.py
happy/commands.py
happy/coverage.py
happy/estimate.py
happy/plot.py
happy/utils.py
happy/tests/__init__.py
happy/tests/test_happy.py
happy_AntoineHo-0.2.1rc0.dist-info/LICENSE
happy_AntoineHo-0.2.1rc0.dist-info/METADATA
happy_AntoineHo-0.2.1rc0.dist-info/WHEEL
happy_AntoineHo-0.2.1rc0.dist-info/entry_points.txt
happy_AntoineHo-0.2.1rc0.dist-info/top_level.txt
happy_AntoineHo-0.2.1rc0.dist-info/RECORD
