Metadata-Version: 2.1
Name: happy-AntoineHo
Version: 0.2.1rc0
Summary: Haploidy with Python
Home-page: https://github.com/AntoineHo/HapPy
Author: Antoine Houtain
Author-email: antoine.houtain@gmail.com
License: UNKNOWN
Platform: UNKNOWN
Classifier: Programming Language :: Python :: 3
Classifier: License :: OSI Approved :: MIT License
Classifier: Operating System :: OS Independent
Requires-Python: >=3.7
Requires-Dist: numpy
Requires-Dist: scipy
Requires-Dist: matplotlib
Requires-Dist: pandas
Requires-Dist: docopt
